checkscore/__init__.py
checkscore/checkscore.py
checkscore/methods.py
checkscore/repeater.py
checkscore-0.2.0.dist-info/LICENSE
checkscore-0.2.0.dist-info/METADATA
checkscore-0.2.0.dist-info/WHEEL
checkscore-0.2.0.dist-info/top_level.txt
checkscore-0.2.0.dist-info/RECORD
