Metadata-Version: 2.1
Name: checkscore
Version: 0.2.0
Summary: A package to auto fill methods in jupyter notebook for SCORE interaction.
Home-page: https://github.com/OpenDevICON/Checkscore
Author: Newton Poudel
Author-email: hinewton25@gmail.com
Classifier: Programming Language :: Python :: 3
Classifier: License :: OSI Approved :: MIT License
Classifier: Operating System :: OS Independent
Requires-Python: >=3.4
License-File: LICENSE
